piratslib/__init__.py
piratslib/common/BaseClasses.py
piratslib/common/__init__.py
piratslib/common/logger.py
piratslib/components/__init__.py
piratslib/components/ADC_PTC_Array/ADCPTCArray.py
piratslib/components/ADC_PTC_Array/__init__.py
piratslib/components/ADS_1018/ADS1018.py
piratslib/components/ADS_1018/ADS1018Consts.py
piratslib/components/ADS_1018/ConfReg.py
piratslib/components/ADS_1018/__init__.py
piratslib/components/ADS_1232/ADS1232.py
piratslib/components/ADS_1232/__init__.py
piratslib/components/GPIO_In/GPIOIn.py
piratslib/components/GPIO_In/__init__.py
piratslib/components/GPIO_Out/GPIOOut.py
piratslib/components/GPIO_Out/__init__.py
piratslib/components/MAX_31865/MAX31865.py
piratslib/components/MAX_31865/__init__.py
piratslib/components/MCP_23S17/MCP23S17.py
piratslib/components/MCP_23S17/__init__.py
piratslib/controlNsensing/DigitalInputSense.py
piratslib/controlNsensing/DigitalOutputControl.py
piratslib/controlNsensing/TemperatureSense.py
piratslib/controlNsensing/VoltageSense.py
piratslib/controlNsensing/WeightSense.py
piratslib/controlNsensing/__init__.py
piratslib/utils/CalcWeight.py
piratslib/utils/LoadCellsZeroCalibration.py
piratslib/utils/__init__.py
piratslib-0.1.6.dist-info/LICENSE
piratslib-0.1.6.dist-info/METADATA
piratslib-0.1.6.dist-info/WHEEL
piratslib-0.1.6.dist-info/top_level.txt
piratslib-0.1.6.dist-info/RECORD
