Metadata-Version: 2.1
Name: piratslib
Version: 0.1.6
Summary: Python Package to interface with PiRATS board hardware devices
Home-page: https://gitlab.pic.es/fcc_control/pirats-lib
Author: Oscar Martínez
Author-email: omartinez@ifae.es
License: CC0 1.0 Universal
Classifier: Development Status :: 4 - Beta
Classifier: Programming Language :: Python :: 3
Provides: piratslib
Requires-Python: >=3
License-File: LICENSE
Requires-Dist: numpy
